pipe2matrix/__init__.py
pipe2matrix/__main__.py
pipe2matrix/main.py
pipe2matrix/matrix_connection.py
pipe2matrix/process_connection.py
pipe2matrix/utils.py
pipe2matrix-0.0.3.dist-info/LICENSE
pipe2matrix-0.0.3.dist-info/METADATA
pipe2matrix-0.0.3.dist-info/WHEEL
pipe2matrix-0.0.3.dist-info/entry_points.txt
pipe2matrix-0.0.3.dist-info/top_level.txt
pipe2matrix-0.0.3.dist-info/RECORD
