Metadata-Version: 2.1
Name: pipe2matrix
Version: 0.0.3
Summary: Redirect input/output of a command into a matrix room
Author-email: Anton Molyboha <anton.stay.connected@gmail.com>
Project-URL: Homepage, https://gitlab.com/anton.molyboha/pipe2matrix
Project-URL: Repository, https://gitlab.com/anton.molyboha/pipe2matrix
Project-URL: Issues, https://gitlab.com/anton.molyboha/pipe2matrix/-/issues
Classifier: Programming Language :: Python :: 3
Classifier: License :: OSI Approved :: GNU General Public License v3 (GPLv3)
Classifier: Operating System :: OS Independent
Requires-Python: >=3.9
License-File: LICENSE
Requires-Dist: matrix-nio >=0.23.0
Requires-Dist: aiofiles >=23.2.1
